nekodata/__init__.py
nekodata/config.py
nekodata/dataset.py
nekodata/example.py
nekodata-0.0.3.dist-info/LICENSE
nekodata-0.0.3.dist-info/METADATA
nekodata-0.0.3.dist-info/WHEEL
nekodata-0.0.3.dist-info/top_level.txt
nekodata-0.0.3.dist-info/RECORD
