Metadata-Version: 2.1
Name: nekodata
Version: 0.0.3
Summary: NekeData is a tools for easy access to meachine learning data.
Home-page: https://github.com/Space-Neko/NekoData
Author: Space Neko AI
Author-email: info@spaceneko.ai
Classifier: Programming Language :: Python :: 3
Classifier: License :: OSI Approved :: MIT License
Classifier: Operating System :: OS Independent
Requires-Python: >=3.7
License-File: LICENSE
